Metadata-Version: 2.1
Name: mixturemm
Version: 0.0.1
Summary: A python package for the simulation and analysis of mixtures in openMM.
Home-page: https://github.com/ColdCoffee97/mixturemm
Author: Benjamin Schmitz
Author-email: benjaminschmitz25@gmail.com
License: MIT license
Keywords: mixturemm
Platform: UNKNOWN
Classifier: Development Status :: 2 - Pre-Alpha
Classifier: Intended Audience :: Developers
Classifier: License :: OSI Approved :: MIT License
Classifier: Natural Language :: English
Classifier: Programming Language :: Python :: 3
Classifier: Programming Language :: Python :: 3.5
Classifier: Programming Language :: Python :: 3.6
Classifier: Programming Language :: Python :: 3.7
Classifier: Programming Language :: Python :: 3.8
Requires-Python: >=3.5
